LICENSE.txt
MANIFEST.in
README.md
setup.py
test_helloworld.py
src/helloworld.py
src/helloworld_serhii73.egg-info/PKG-INFO
src/helloworld_serhii73.egg-info/SOURCES.txt
src/helloworld_serhii73.egg-info/dependency_links.txt
src/helloworld_serhii73.egg-info/top_level.txt