Metadata-Version: 2.1
Name: helloworld-serhii73
Version: 0.0.1
Summary: Say hello!
Home-page: https://github.com/serhii73/helloworld
Author: Serhii
Author-email: aserhii@protonmail.com
License: UNKNOWN
Platform: UNKNOWN
Classifier: Programming Language :: Python :: 3
Classifier: Programming Language :: Python :: 3.6
Classifier: Programming Language :: Python :: 3.7
Classifier: License :: OSI Approved :: GNU General Public License v2 or later (GPLv2+)
Classifier: Operating System :: OS Independent
